Workbook

Sheet GHG Summary
A1: AsterChem 2025 GHG Inventory
A3: Inventory component | B3: Emissions (tCO₂e) | C3: Share of market-based total | E3: Scope 2 comparison
A4: Scope 1 | B4: ='Scope 1 Data'!M17 -> 64217.142 | C4: =B4/B$10 -> 0.24040718 | E4: Location-based | F4: =B5 -> 42084
A5: Scope 2 Location-Based | B5: ='Scope 2 Data'!P11 -> 42084 | E5: Market-based | F5: =B6 -> 20949
A6: Scope 2 Market-Based | B6: ='Scope 2 Data'!Q11 -> 20949 | C6: =B6/B$10 -> 0.078425946 | E6: Absolute difference | F6: =F4-F5 -> 21135
A7: Scope 3 | B7: ='Scope 3 Data'!R20 -> 181952.09 | C7: =B7/B$10 -> 0.68116687 | E7: Percentage difference | F7: =F6/F4 -> 0.50220987
A9: Total Location-Based Inventory | B9: =B4+B5+B7 -> 288253.23
A10: Total Market-Based Inventory | B10: =B4+B6+B7 -> 267118.23
A11: Percentage Check | C11: =SUM(C4,C6,C7) -> 1
A13: Total production (tonnes) | B13: =SUM('Company Data'!E15:E17) -> 167000
A14: Market-based emissions intensity | B14: =B10/B13 -> 1.5995104 | C14: tCO₂e per tonne of product
A16: Revenue (USD million) | B16: ='Company Data'!B11/1000000 -> 486
A17: Revenue emissions intensity | B17: =B10/B16 -> 549.62599 | C17: tCO₂e per USD million revenue
A19: Largest Category Value from Scope 3 | B19: ='Scope 3 Data'!R23 -> Purchased goods and services
A21: Largest-Scope Emissions | B21: =MAX(B4,B6,B7) -> 181952.09 | C21: tCO₂e
A22: Largest Overall Scope | B22: =IF(B4=MAX(B4,B6,B7),A4,IF(B6=MAX(B4,B6,B7),A6,A7)) -> Scope 3

Sheet Company Data
A1: AsterChem Specialty Chemicals Ltd — company data
A2: The workbook calculates a synthetic Scope 1, Scope 2 and Scope 3 inventory for educational and portfolio purposes
A4: Company field | B4: Value
A5: Reporting year | B5: 2025
A6: Industry | B6: Specialty chemicals: resins and industrial solvents
A7: Consolidation approach | B7: Operational control
A8: Headquarters | B8: Manchester, United Kingdom
A9: Reporting currency | B9: USD
A10: Employees | B10: 1280
A11: Revenue (USD) | B11: 486000000
A12: Dataset status | B12: Synthetic; educational use only
A14: Site ID | B14: Site | C14: Country | D14: Primary activity | E14: Production output (tonnes) | F14: Employees | G14: Owned or leased | H14: Operational control?
A15: SITE-UK | B15: Northport Plant | C15: United Kingdom | D15: Specialty resins | E15: 42000 | F15: 360 | G15: Owned | H15: Yes
A16: SITE-DE | B16: Rheinhafen Plant | C16: Germany | D16: Industrial solvents | E16: 58000 | F16: 410 | G16: Owned | H16: Yes
A17: SITE-US | B17: Riverbend Plant | C17: United States | D17: Specialty resins and intermediates | E17: 67000 | F17: 510 | G17: Owned | H17: Yes

Sheet Scope 1 Data
A1: Scope 1 raw activity data
A2: Direct sources controlled by AsterChem. Factor values are located on the Emission Factors sheet; this sheet contains no emissions calculations.
A4: Record ID | B4: Site ID | C4: Site | D4: Country | E4: Source type | F4: Activity description | G4: Activity amount | H4: Activity unit | I4: Factor ID | J4: Evidence type | K4: Additional information | L4: Emission Factor | M4: Emission (tCO2e) | N4: Unit | O4: Source | P4: Sum of Source type
A5: S1-001 | B5: SITE-UK | C5: Northport Plant | D5: United Kingdom | E5: Stationary combustion | F5: Natural gas used in boilers and thermal oxidizer | G5: 48500000 | H5: kWh | I5: NG-KWH | J5: Meter readings | K5: Annual total | L5: =VLOOKUP(I5,'Emission Factors'!$A$5:$G$38,3,) -> 0.202 | M5: =G5*L5/1000 -> 9797 | N5: Tonnes | O5: Stationary Combustion | P5: =SUMIF($E$5:$E$16,"Stationary combustion",$M$5:$M$16) -> 37006.4
A6: S1-002 | B6: SITE-UK | C6: Northport Plant | D6: United Kingdom | E6: Mobile combustion | F6: Diesel used by forklifts and site vehicles | G6: 145000 | H6: litre | I6: DIESEL-L | J6: Fuel invoices | K6: Company-controlled fleet | L6: =VLOOKUP(I6,'Emission Factors'!$A$5:$G$38,3,) -> 2.68 | M6: =G6*L6/1000 -> 388.6 | N6: Tonnes | O6: Mobile Combustion | P6: =SUMIF($E$5:$E$16,"Mobile combustion",$M$5:$M$16) -> 1308.7
A7: S1-003 | B7: SITE-UK | C7: Northport Plant | D7: United Kingdom | E7: Process emissions | F7: Specialty resin manufactured | G7: 42000 | H7: tonne product | I7: PROC-RESIN | J7: Production records | K7: Reaction and vent emissions | L7: =VLOOKUP(I7,'Emission Factors'!$A$5:$G$38,3,) -> 185 | M7: =G7*L7/1000 -> 7770 | N7: Tonnes | O7: Process Emissions | P7: =SUMIF($E$5:$E$16,"Process emissions",$M$5:$M$16) -> 25501
A8: S1-004 | B8: SITE-UK | C8: Northport Plant | D8: United Kingdom | E8: Fugitive emissions | F8: R-134a refrigerant leaked | G8: 82 | H8: kg leaked | I8: R134A-KG | J8: Maintenance logs | K8: Cooling systems | L8: =VLOOKUP(I8,'Emission Factors'!$A$5:$G$38,3,) -> 1430 | M8: =G8*L8/1000 -> 117.26 | N8: Tonnes | O8: Fugitive Emissions | P8: =SUMIF($E$5:$E$16,"Fugitive emissions",$M$5:$M$16) -> 401.042
A9: S1-005 | B9: SITE-DE | C9: Rheinhafen Plant | D9: Germany | E9: Stationary combustion | F9: Natural gas used in steam boilers | G9: 61200000 | H9: kWh | I9: NG-KWH | J9: Meter readings | K9: Annual total | L9: =VLOOKUP(I9,'Emission Factors'!$A$5:$G$38,3,) -> 0.202 | M9: =G9*L9/1000 -> 12362.4 | N9: Tonnes
A10: S1-006 | B10: SITE-DE | C10: Rheinhafen Plant | D10: Germany | E10: Mobile combustion | F10: LPG used by material-handling equipment | G10: 210000 | H10: litre | I10: LPG-L | J10: Fuel invoices | K10: Company-controlled equipment | L10: =VLOOKUP(I10,'Emission Factors'!$A$5:$G$38,3,) -> 1.51 | M10: =G10*L10/1000 -> 317.1 | N10: Tonnes
A11: S1-007 | B11: SITE-DE | C11: Rheinhafen Plant | D11: Germany | E11: Process emissions | F11: Industrial solvent manufactured | G11: 58000 | H11: tonne product | I11: PROC-SOLV | J11: Production records | K11: Distillation and vent emissions | L11: =VLOOKUP(I11,'Emission Factors'!$A$5:$G$38,3,) -> 92 | M11: =G11*L11/1000 -> 5336 | N11: Tonnes
A12: S1-008 | B12: SITE-DE | C12: Rheinhafen Plant | D12: Germany | E12: Fugitive emissions | F12: R-410A refrigerant leaked | G12: 64 | H12: kg leaked | I12: R410A-KG | J12: Maintenance logs | K12: HVAC and chillers | L12: =VLOOKUP(I12,'Emission Factors'!$A$5:$G$38,3,) -> 2088 | M12: =G12*L12/1000 -> 133.632 | N12: Tonnes
A13: S1-009 | B13: SITE-US | C13: Riverbend Plant | D13: United States | E13: Stationary combustion | F13: Natural gas used for process heat | G13: 73500000 | H13: kWh | I13: NG-KWH | J13: Meter readings | K13: Annual total | L13: =VLOOKUP(I13,'Emission Factors'!$A$5:$G$38,3,) -> 0.202 | M13: =G13*L13/1000 -> 14847 | N13: Tonnes
A14: S1-010 | B14: SITE-US | C14: Riverbend Plant | D14: United States | E14: Mobile combustion | F14: Diesel used by on-site fleet | G14: 225000 | H14: litre | I14: DIESEL-L | J14: Fuel invoices | K14: Company-controlled fleet | L14: =VLOOKUP(I14,'Emission Factors'!$A$5:$G$38,3,) -> 2.68 | M14: =G14*L14/1000 -> 603 | N14: Tonnes
A15: S1-011 | B15: SITE-US | C15: Riverbend Plant | D15: United States | E15: Process emissions | F15: Specialty resin and intermediates manufactured | G15: 67000 | H15: tonne product | I15: PROC-RESIN | J15: Production records | K15: Reaction and vent emissions | L15: =VLOOKUP(I15,'Emission Factors'!$A$5:$G$38,3,) -> 185 | M15: =G15*L15/1000 -> 12395 | N15: Tonnes
A16: S1-012 | B16: SITE-US | C16: Riverbend Plant | D16: United States | E16: Fugitive emissions | F16: R-134a refrigerant leaked | G16: 105 | H16: kg leaked | I16: R134A-KG | J16: Maintenance logs | K16: Cooling systems | L16: =VLOOKUP(I16,'Emission Factors'!$A$5:$G$38,3,) -> 1430 | M16: =G16*L16/1000 -> 150.15 | N16: Tonnes
L17: Total= | M17: =SUM(M5:M16) -> 64217.142 | N17: Tonnes

Sheet Scope 2 Data
A1: Scope 2 raw activity data
A2: Purchased electricity and steam. Location-based and market-based factor IDs are both supplied, but no Scope 2 result is calculated.
A4: Record ID | B4: Site ID | C4: Site | D4: Country | E4: Purchased energy | F4: Activity amount | G4: Activity unit | H4: Location factor ID | I4: Market factor ID | J4: Renewable share | K4: Evidence type | L4: Contractual instrument | M4: Reporting note | N4: Location Based Factor | O4: Market Based Factor | P4: Location Based Emissions (tCO2e) | Q4: Market Based Emissions (tCO2e)
A5: S2-001 | B5: SITE-UK | C5: Northport Plant | D5: United Kingdom | E5: Electricity | F5: 28400 | G5: MWh | H5: ELEC-UK | I5: ELEC-MKT-UK | J5: 0.55 | K5: Utility invoices | L5: Renewable supply contract | M5: Calculate both methods | N5: =VLOOKUP(H5,'Emission Factors'!$A$5:$G$38,3,) -> 0.207 | O5: =VLOOKUP(I5,'Emission Factors'!A$5:G$38,3,) -> 0.095 | P5: =F5*N5 -> 5878.8 | Q5: =F5*O5 -> 2698
A6: S2-002 | B6: SITE-UK | C6: Northport Plant | D6: United Kingdom | E6: Steam | F6: 9200 | G6: MWh | H6: STEAM-KWH | I6: STEAM-KWH | J6: 0 | K6: Supplier statement | L6: None | M6: Same factor for both methods | N6: =VLOOKUP(H6,'Emission Factors'!$A$5:$G$38,3,) -> 0.17 | O6: =VLOOKUP(I6,'Emission Factors'!A$5:G$38,3,) -> 0.17 | P6: =F6*N6 -> 1564 | Q6: =F6*O6 -> 1564 | S6: %Difference | T6: =((P11-Q11)/P11) -> 0.50220987
A7: S2-003 | B7: SITE-DE | C7: Rheinhafen Plant | D7: Germany | E7: Electricity | F7: 36100 | G7: MWh | H7: ELEC-DE | I7: ELEC-MKT-DE | J7: 0.72 | K7: Utility invoices | L7: Renewable supply contract | M7: Calculate both methods | N7: =VLOOKUP(H7,'Emission Factors'!$A$5:$G$38,3,) -> 0.366 | O7: =VLOOKUP(I7,'Emission Factors'!A$5:G$38,3,) -> 0.12 | P7: =F7*N7 -> 13212.6 | Q7: =F7*O7 -> 4332
A8: S2-004 | B8: SITE-DE | C8: Rheinhafen Plant | D8: Germany | E8: Steam | F8: 11800 | G8: MWh | H8: STEAM-KWH | I8: STEAM-KWH | J8: 0 | K8: Supplier statement | L8: None | M8: District steam | N8: =VLOOKUP(H8,'Emission Factors'!$A$5:$G$38,3,) -> 0.17 | O8: =VLOOKUP(I8,'Emission Factors'!A$5:G$38,3,) -> 0.17 | P8: =F8*N8 -> 2006 | Q8: =F8*O8 -> 2006
A9: S2-005 | B9: SITE-US | C9: Riverbend Plant | D9: United States | E9: Electricity | F9: 42800 | G9: MWh | H9: ELEC-USMW | I9: ELEC-MKT-US | J9: 0.38 | K9: Utility invoices | L9: Renewable energy certificates | M9: Calculate both methods | N9: =VLOOKUP(H9,'Emission Factors'!$A$5:$G$38,3,) -> 0.397 | O9: =VLOOKUP(I9,'Emission Factors'!A$5:G$38,3,) -> 0.185 | P9: =F9*N9 -> 16991.6 | Q9: =F9*O9 -> 7918
A10: S2-006 | B10: SITE-US | C10: Riverbend Plant | D10: United States | E10: Steam | F10: 14300 | G10: MWh | H10: STEAM-KWH | I10: STEAM-KWH | J10: 0 | K10: Supplier statement | L10: None | M10: Third-party steam | N10: =VLOOKUP(H10,'Emission Factors'!$A$5:$G$38,3,) -> 0.17 | O10: =VLOOKUP(I10,'Emission Factors'!A$5:G$38,3,) -> 0.17 | P10: =F10*N10 -> 2431 | Q10: =F10*O10 -> 2431
O11: Total= | P11: =SUM(P5:P10) -> 42084 | Q11: =SUM(Q5:Q10) -> 20949

Sheet Scope 3 Data
A1: Scope 3 raw activity data
A2: All 15 Scope 3 categories are represented. No category emissions, subtotals, or total footprint are included.
A4: Record ID | B4: Category | C4: Category name | D4: Activity description | E4: Activity amount | F4: Activity unit | G4: Factor ID | H4: Data source | I4: Calculation approach | J4: Included in inventory? | K4: Exclusion or boundary reason | L4: Data-quality level | M4: Emission Factor | N4: Emissions (tCO2e) | O4: Unit | P4: Category | Q4: Category Name | R4: Emissions | S4: Share of Scope 3 | T4: % Share
A5: S3-001 | B5: 1 | C5: Purchased goods and services | D5: Methanol purchased | E5: 62000 | F5: tonne | G5: MAT-METH | H5: Procurement records | I5: Physical activity | J5: Yes | L5: High | M5: =VLOOKUP(G5,'Emission Factors'!A$5:G$38,3,) -> 730 | N5: =IF(J5 = "Yes",M5*E5/1000,0) -> 45260 | O5: Tonnes | P5: 1 | Q5: Purchased goods and services | R5: =SUMIF(B$5:B$26,P5,N$5:N$26) -> 85920 | S5: =R5/N$27 -> 0.47221222 | T5: =S5*100 -> 47.221222
A6: S3-002 | B6: 1 | C6: Purchased goods and services | D6: Organic acid purchased | E6: 27500 | F6: tonne | G6: MAT-ACID | H6: Procurement records | I6: Physical activity | J6: Yes | L6: High | M6: =VLOOKUP(G6,'Emission Factors'!A$5:G$38,3,) -> 1120 | N6: =IF(J6 = "Yes",M6*E6/1000,0) -> 30800 | O6: Tonnes | P6: 2 | Q6: Capital goods | R6: =SUMIF(B$5:B$26,P6,N$5:N$26) -> 5735 | S6: =R6/N$27 -> 0.031519286 | T6: =S6*100 -> 3.1519286
A7: S3-003 | B7: 1 | C7: Purchased goods and services | D7: Packaging purchased | E7: 6800 | F7: tonne | G7: MAT-PACK | H7: Procurement records | I7: Physical activity | J7: Yes | L7: High | M7: =VLOOKUP(G7,'Emission Factors'!A$5:G$38,3,) -> 1450 | N7: =IF(J7 = "Yes",M7*E7/1000,0) -> 9860 | O7: Tonnes | P7: 3 | Q7: Fuel- and energy-related activities | R7: =SUMIF(B$5:B$26,P7,N$5:N$26) -> 8848.5 | S7: =R7/N$27 -> 0.048630934 | T7: =S7*100 -> 4.8630934
A8: S3-004 | B8: 2 | C8: Capital goods | D8: New reactor and site equipment | E8: 18500000 | F8: USD | G8: CAPEX-USD | H8: Capital ledger | I8: Spend based | J8: Yes | L8: Medium | M8: =VLOOKUP(G8,'Emission Factors'!A$5:G$38,3,) -> 0.31 | N8: =IF(J8 = "Yes",M8*E8/1000,0) -> 5735 | O8: Tonnes | P8: 4 | Q8: Upstream transportation and distribution | R8: =SUMIF(B$5:B$26,P8,N$5:N$26) -> 2633 | S8: =R8/N$27 -> 0.014470842 | T8: =S8*100 -> 1.4470842
A9: S3-005 | B9: 3 | C9: Fuel- and energy-related activities | D9: Upstream natural gas | E9: 183200000 | F9: kWh | G9: WTT-NG | H9: Energy records | I9: Physical activity | J9: Yes | K9: Excludes direct combustion already in Scope 1 | L9: High | M9: =VLOOKUP(G9,'Emission Factors'!A$5:G$38,3,) -> 0.036 | N9: =IF(J9 = "Yes",M9*E9/1000,0) -> 6595.2 | O9: Tonnes | P9: 5 | Q9: Waste generated in operations | R9: =SUMIF(B$5:B$26,P9,N$5:N$26) -> 1992 | S9: =R9/N$27 -> 0.010947937 | T9: =S9*100 -> 1.0947937
A10: S3-006 | B10: 3 | C10: Fuel- and energy-related activities | D10: Electricity transmission and distribution losses | E10: 107300000 | F10: kWh | G10: WTT-ELEC | H10: Electricity records | I10: Physical activity | J10: Yes | K10: Excludes generation emissions already in Scope 2 | L10: High | M10: =VLOOKUP(G10,'Emission Factors'!A$5:G$38,3,) -> 0.021 | N10: =IF(J10 = "Yes",M10*E10/1000,0) -> 2253.3 | O10: Tonnes | P10: 6 | Q10: Business travel | R10: =SUMIF(B$5:B$26,P10,N$5:N$26) -> 492.34 | S10: =R10/N$27 -> 0.0027058771 | T10: =S10*100 -> 0.27058771
A11: S3-007 | B11: 4 | C11: Upstream transportation and distribution | D11: Inbound road freight | E11: 18600000 | F11: tonne-km | G11: FREIGHT-ROAD | H11: Logistics records | I11: Distance based | J11: Yes | L11: Medium | M11: =VLOOKUP(G11,'Emission Factors'!A$5:G$38,3,) -> 0.105 | N11: =IF(J11 = "Yes",M11*E11/1000,0) -> 1953 | O11: Tonnes | P11: 7 | Q11: Employee commuting | R11: =SUMIF(B$5:B$26,P11,N$5:N$26) -> 1033.2 | S11: =R11/N$27 -> 0.0056784179 | T11: =S11*100 -> 0.56784179
A12: S3-008 | B12: 4 | C12: Upstream transportation and distribution | D12: Inbound sea freight | E12: 42500000 | F12: tonne-km | G12: FREIGHT-SEA | H12: Logistics records | I12: Distance based | J12: Yes | L12: Medium | M12: =VLOOKUP(G12,'Emission Factors'!A$5:G$38,3,) -> 0.016 | N12: =IF(J12 = "Yes",M12*E12/1000,0) -> 680 | O12: Tonnes | P12: 8 | Q12: Upstream leased assets | R12: =SUMIF(B$5:B$26,P12,N$5:N$26) -> 0 | S12: =R12/N$27 -> 0 | T12: =S12*100 -> 0
A13: S3-009 | B13: 5 | C13: Waste generated in operations | D13: Hazardous waste sent to landfill | E13: 920 | F13: tonne | G13: WASTE-LF | H13: Waste manifests | I13: Waste specific | J13: Yes | L13: High | M13: =VLOOKUP(G13,'Emission Factors'!A$5:G$38,3,) -> 610 | N13: =IF(J13 = "Yes",M13*E13/1000,0) -> 561.2 | O13: Tonnes | P13: 9 | Q13: Downstream transportation and distribution | R13: =SUMIF(B$5:B$26,P13,N$5:N$26) -> 3163.8 | S13: =R13/N$27 -> 0.017388094 | T13: =S13*100 -> 1.7388094
A14: S3-010 | B14: 5 | C14: Waste generated in operations | D14: Hazardous waste incinerated | E14: 1460 | F14: tonne | G14: WASTE-INC | H14: Waste manifests | I14: Waste specific | J14: Yes | L14: High | M14: =VLOOKUP(G14,'Emission Factors'!A$5:G$38,3,) -> 980 | N14: =IF(J14 = "Yes",M14*E14/1000,0) -> 1430.8 | O14: Tonnes | P14: 10 | Q14: Processing of sold products | R14: =SUMIF(B$5:B$26,P14,N$5:N$26) -> 33210 | S14: =R14/N$27 -> 0.18252057 | T14: =S14*100 -> 18.252057
A15: S3-011 | B15: 6 | C15: Business travel | D15: Air travel | E15: 2950000 | F15: passenger-km | G15: AIR-PKM | H15: Travel provider | I15: Distance based | J15: Yes | L15: Medium | M15: =VLOOKUP(G15,'Emission Factors'!A$5:G$38,3,) -> 0.158 | N15: =IF(J15 = "Yes",M15*E15/1000,0) -> 466.1 | O15: Tonnes | P15: 11 | Q15: Use of sold products | R15: =SUMIF(B$5:B$26,P15,N$5:N$26) -> 14820 | S15: =R15/N$27 -> 0.081450012 | T15: =S15*100 -> 8.1450012
A16: S3-012 | B16: 6 | C16: Business travel | D16: Rail travel | E16: 640000 | F16: passenger-km | G16: RAIL-PKM | H16: Travel provider | I16: Distance based | J16: Yes | L16: Medium | M16: =VLOOKUP(G16,'Emission Factors'!A$5:G$38,3,) -> 0.041 | N16: =IF(J16 = "Yes",M16*E16/1000,0) -> 26.24 | O16: Tonnes | P16: 12 | Q16: End-of-life treatment of sold products | R16: =SUMIF(B$5:B$26,P16,N$5:N$26) -> 19706 | S16: =R16/N$27 -> 0.10830324 | T16: =S16*100 -> 10.830324
A17: S3-013 | B17: 7 | C17: Employee commuting | D17: Employee commuting | E17: 8200000 | F17: employee-km | G17: COMMUTE-KM | H17: Employee survey | I17: Survey extrapolation | J17: Yes | L17: Low | M17: =VLOOKUP(G17,'Emission Factors'!A$5:G$38,3,) -> 0.126 | N17: =IF(J17 = "Yes",M17*E17/1000,0) -> 1033.2 | O17: Tonnes | P17: 13 | Q17: Downstream leased assets | R17: =SUMIF(B$5:B$26,P17,N$5:N$26) -> 416.25 | S17: =R17/N$27 -> 0.0022876901 | T17: =S17*100 -> 0.22876901
A18: S3-014 | B18: 8 | C18: Upstream leased assets | D18: Leased warehouses | E18: 0 | F18: kWh | G18: LEASE-KWH | H18: Boundary assessment | I18: Not applicable | J18: No | K18: Assets are inside operational boundary and covered by Scopes 1 and 2 | L18: High | M18: =VLOOKUP(G18,'Emission Factors'!A$5:G$38,3,) -> 0.245 | N18: =IF(J18 = "Yes",M18*E18/1000,0) -> 0 | O18: Tonnes | P18: 14 | Q18: Franchises | R18: =SUMIF(B$5:B$26,P18,N$5:N$26) -> 357 | S18: =R18/N$27 -> 0.001962055 | T18: =S18*100 -> 0.1962055
A19: S3-015 | B19: 9 | C19: Downstream transportation and distribution | D19: Outbound road freight | E19: 21400000 | F19: tonne-km | G19: FREIGHT-ROAD | H19: Distribution records | I19: Distance based | J19: Yes | L19: Medium | M19: =VLOOKUP(G19,'Emission Factors'!A$5:G$38,3,) -> 0.105 | N19: =IF(J19 = "Yes",M19*E19/1000,0) -> 2247 | O19: Tonnes | P19: 15 | Q19: Investments | R19: =SUMIF(B$5:B$26,P19,N$5:N$26) -> 3625 | S19: =R19/N$27 -> 0.019922827 | T19: =S19*100 -> 1.9922827
A20: S3-016 | B20: 9 | C20: Downstream transportation and distribution | D20: Outbound sea freight | E20: 57300000 | F20: tonne-km | G20: FREIGHT-SEA | H20: Distribution records | I20: Distance based | J20: Yes | L20: Medium | M20: =VLOOKUP(G20,'Emission Factors'!A$5:G$38,3,) -> 0.016 | N20: =IF(J20 = "Yes",M20*E20/1000,0) -> 916.8 | O20: Tonnes | Q20: Check Total= | R20: =SUM(R5:R19) -> 181952.09 | S20: =R20/N$27 -> 1 | T20: =S20*100 -> 100
A21: S3-017 | B21: 10 | C21: Processing of sold products | D21: Customer processing of intermediates | E21: 81000 | F21: tonne sold | G21: PROCESS-SOLD | H21: Sales records | I21: Average processing factor | J21: Yes | L21: Medium | M21: =VLOOKUP(G21,'Emission Factors'!A$5:G$38,3,) -> 410 | N21: =IF(J21 = "Yes",M21*E21/1000,0) -> 33210 | O21: Tonnes
A22: S3-018 | B22: 11 | C22: Use of sold products | D22: Lifetime use of solvent products | E22: 57000 | F22: tonne sold | G22: USE-SOLD | H22: Sales records | I22: Average use-phase factor | J22: Yes | L22: Low | M22: =VLOOKUP(G22,'Emission Factors'!A$5:G$38,3,) -> 260 | N22: =IF(J22 = "Yes",M22*E22/1000,0) -> 14820 | O22: Tonnes
A23: S3-019 | B23: 12 | C23: End-of-life treatment of sold products | D23: Sold products reaching end of life | E23: 167000 | F23: tonne sold | G23: EOL-PROD | H23: Sales and composition records | I23: Average disposal mix | J23: Yes | L23: Low | M23: =VLOOKUP(G23,'Emission Factors'!A$5:G$38,3,) -> 118 | N23: =IF(J23 = "Yes",M23*E23/1000,0) -> 19706 | O23: Tonnes | Q23: Largest Category Value | R23: =INDEX(Q5:Q19,MATCH(MAX(R5:R19),R5:R19,0)) -> Purchased goods and services
A24: S3-020 | B24: 13 | C24: Downstream leased assets | D24: Leased dosing equipment energy | E24: 1850000 | F24: kWh | G24: LEASE-DOWN | H24: Customer estimates | I24: Energy based | J24: Yes | L24: Low | M24: =VLOOKUP(G24,'Emission Factors'!A$5:G$38,3,) -> 0.225 | N24: =IF(J24 = "Yes",M24*E24/1000,0) -> 416.25 | O24: Tonnes
A25: S3-021 | B25: 14 | C25: Franchises | D25: Licensed blending locations | E25: 2100000 | F25: USD | G25: FRANCH-USD | H25: Franchise declarations | I25: Spend based | J25: Yes | L25: Low | M25: =VLOOKUP(G25,'Emission Factors'!A$5:G$38,3,) -> 0.17 | N25: =IF(J25 = "Yes",M25*E25/1000,0) -> 357 | O25: Tonnes
A26: S3-022 | B26: 15 | C26: Investments | D26: Minority joint venture investment | E26: 12500000 | F26: USD invested | G26: INVEST-USD | H26: Finance records | I26: Spend-based proxy | J26: Yes | L26: Low | M26: =VLOOKUP(G26,'Emission Factors'!A$5:G$38,3,) -> 0.29 | N26: =IF(J26 = "Yes",M26*E26/1000,0) -> 3625 | O26: Tonnes
M27: Total= | N27: =SUM(N5:N26) -> 181952.09 | O27: Tonnes

Sheet Emission Factors
A1: Synthetic emission-factor library
A2: Illustrative factors only. Replace them with authoritative factors that match the reporting year, geography, technology, and accounting standard.
A4: Factor ID | B4: Emission source | C4: Factor value | D4: Factor unit | E4: Geography | F4: Factor type | G4: Basis
A5: NG-KWH | B5: Natural gas combustion | C5: 0.202 | D5: kgCO2e/kWh | E5: Generic | F5: Combustion | G5: Synthetic rounded value
A6: DIESEL-L | B6: Diesel combustion | C6: 2.68 | D6: kgCO2e/litre | E6: Generic | F6: Combustion | G6: Synthetic rounded value
A7: LPG-L | B7: LPG combustion | C7: 1.51 | D7: kgCO2e/litre | E7: Generic | F7: Combustion | G7: Synthetic rounded value
A8: PROC-RESIN | B8: Resin process releases | C8: 185 | D8: kgCO2e/tonne product | E8: Generic | F8: Process | G8: Synthetic process estimate
A9: PROC-SOLV | B9: Solvent process releases | C9: 92 | D9: kgCO2e/tonne product | E9: Generic | F9: Process | G9: Synthetic process estimate
A10: R134A-KG | B10: R-134a leakage | C10: 1430 | D10: kgCO2e/kg leaked | E10: Generic | F10: Fugitive | G10: Illustrative GWP-based value
A11: R410A-KG | B11: R-410A leakage | C11: 2088 | D11: kgCO2e/kg leaked | E11: Generic | F11: Fugitive | G11: Illustrative GWP-based value
A12: ELEC-UK | B12: Grid electricity | C12: 0.207 | D12: kgCO2e/kWh | E12: United Kingdom | F12: Location based | G12: Synthetic regional value
A13: ELEC-DE | B13: Grid electricity | C13: 0.366 | D13: kgCO2e/kWh | E13: Germany | F13: Location based | G13: Synthetic regional value
A14: ELEC-USMW | B14: Grid electricity | C14: 0.397 | D14: kgCO2e/kWh | E14: United States Midwest | F14: Location based | G14: Synthetic regional value
A15: ELEC-MKT-UK | B15: Contractual electricity | C15: 0.095 | D15: kgCO2e/kWh | E15: United Kingdom | F15: Market based | G15: Synthetic supplier value
A16: ELEC-MKT-DE | B16: Contractual electricity | C16: 0.12 | D16: kgCO2e/kWh | E16: Germany | F16: Market based | G16: Synthetic supplier value
... A38: INVEST-USD | B38: Investments | C38: 0.29 | D38: kgCO2e/USD invested | E38: Generic | F38: Spend based | G38: Synthetic proxy
